[[0.153381,{"lines":{"0":[["                                                                                ",{}]],"1":[["                                                                                ",{}]],"2":[["                                                                                ",{}]],"3":[["                                                                                ",{}]],"4":[["                                                                                ",{}]],"5":[["                                                                                ",{}]],"6":[["                                                                                ",{}]],"7":[["                                                                                ",{}]],"8":[["                                                                                ",{}]],"9":[["                                                                                ",{}]],"10":[["                                                                                ",{}]],"11":[["                                                                                ",{}]],"12":[["                                                                                ",{}]],"13":[["                                                                                ",{}]],"14":[["                                                                                ",{}]],"15":[["                                                                                ",{}]],"16":[["                                                                                ",{}]],"17":[["                                                                                ",{}]],"18":[["                                                                                ",{}]],"19":[["                                                                                ",{}]],"20":[["                                                                                ",{}]],"21":[["                                                                                ",{}]],"22":[["                                                                                ",{}]],"23":[["                                                                                ",{}]]},"cursor":{"x":0,"y":1,"visible":true}}],[0.003847,{"lines":{"1":[["        G N U P L O T                                                           ",{}]],"2":[["        Version 4.6 patchlevel 5 (Gentoo revision r0)    last modified 2014-02-2",{}]],"3":[["6                                                                               ",{}]],"4":[["        Build System: Linux i686                                                ",{}]],"6":[["        Copyright (C) 1986-1993, 1998, 2004, 2007-2014                          ",{}]],"7":[["        Thomas Williams, Colin Kelley and many others                           ",{}]],"9":[["        gnuplot home:     http://www.gnuplot.info                               ",{}]],"10":[["        faq, bugs, etc:   type \"help FAQ\"                                       ",{}]],"11":[["        immediate help:   type \"help\"  (plot window: hit 'h')                   ",{}]],"13":[["Terminal type set to 'qt'                                                       ",{}]],"14":[["gnuplot>                                                                        ",{}]]},"cursor":{"x":9,"y":14}}],[1.841601,{"lines":{"14":[["gnuplot> s                                                                      ",{}]]},"cursor":{"x":10}}],[0.08469599999999999,{"lines":{"14":[["gnuplot> se                                                                     ",{}]]},"cursor":{"x":11}}],[0.185985,{"lines":{"14":[["gnuplot> set                                                                    ",{}]]},"cursor":{"x":12}}],[0.193464,{"cursor":{"x":13}}],[0.156758,{"lines":{"14":[["gnuplot> set t                                                                  ",{}]]},"cursor":{"x":14}}],[0.092849,{"lines":{"14":[["gnuplot> set te                                                                 ",{}]]},"cursor":{"x":15}}],[0.146408,{"lines":{"14":[["gnuplot> set ter                                                                ",{}]]},"cursor":{"x":16}}],[0.058698,{"lines":{"14":[["gnuplot> set term                                                               ",{}]]},"cursor":{"x":17}}],[0.101447,{"lines":{"14":[["gnuplot> set termi                                                              ",{}]]},"cursor":{"x":18}}],[0.199501,{"lines":{"14":[["gnuplot> set termin                                                             ",{}]]},"cursor":{"x":19}}],[0.159461,{"lines":{"14":[["gnuplot> set termina                                                            ",{}]]},"cursor":{"x":20}}],[0.134615,{"lines":{"14":[["gnuplot> set terminal                                                           ",{}]]},"cursor":{"x":21}}],[0.232993,{"cursor":{"x":22}}],[0.432199,{"lines":{"14":[["gnuplot> set terminal d                                                         ",{}]]},"cursor":{"x":23}}],[0.103505,{"lines":{"14":[["gnuplot> set terminal du                                                        ",{}]]},"cursor":{"x":24}}],[0.187809,{"lines":{"14":[["gnuplot> set terminal dum                                                       ",{}]]},"cursor":{"x":25}}],[0.125905,{"lines":{"14":[["gnuplot> set terminal dumb                                                      ",{}]]},"cursor":{"x":26}}],[0.159534,{"lines":{"15":[["Terminal type set to 'dumb'                                                     ",{}]],"16":[["Options are 'feed  size 79, 24'                                                 ",{}]],"17":[["gnuplot>                                                                        ",{}]]},"cursor":{"x":9,"y":17}}],[2.330546,{"lines":{"17":[["gnuplot> #                                                                      ",{}]]},"cursor":{"x":10}}],[0.24211,{"cursor":{"x":11}}],[0.384267,{"lines":{"17":[["gnuplot> # 3                                                                    ",{}]]},"cursor":{"x":12}}],[0.154412,{"lines":{"17":[["gnuplot> # 3d                                                                   ",{}]]},"cursor":{"x":13}}],[0.493719,{"cursor":{"x":14}}],[0.477317,{"cursor":{"x":13}}],[0.156538,{"lines":{"17":[["gnuplot> # 3                                                                    ",{}]]},"cursor":{"x":12}}],[0.1483,{"lines":{"17":[["gnuplot> #                                                                      ",{}]]},"cursor":{"x":11}}],[0.179251,{"lines":{"17":[["gnuplot> # 2                                                                    ",{}]]},"cursor":{"x":12}}],[0.662531,{"lines":{"17":[["gnuplot> # 2d                                                                   ",{}]]},"cursor":{"x":13}}],[0.131559,{"cursor":{"x":14}}],[0.249361,{"lines":{"17":[["gnuplot> # 2d p                                                                 ",{}]]},"cursor":{"x":15}}],[0.244909,{"lines":{"17":[["gnuplot> # 2d pl                                                                ",{}]]},"cursor":{"x":16}}],[0.141447,{"lines":{"17":[["gnuplot> # 2d plo                                                               ",{}]]},"cursor":{"x":17}}],[0.112011,{"lines":{"17":[["gnuplot> # 2d plot                                                              ",{}]]},"cursor":{"x":18}}],[0.339013,{"lines":{"18":[["gnuplot>                                                                        ",{}]]},"cursor":{"x":9,"y":18}}],[1.796573,{"lines":{"18":[["gnuplot> p                                                                      ",{}]]},"cursor":{"x":10}}],[0.181663,{"lines":{"18":[["gnuplot> pl                                                                     ",{}]]},"cursor":{"x":11}}],[0.150899,{"lines":{"18":[["gnuplot> plo                                                                    ",{}]]},"cursor":{"x":12}}],[0.122918,{"lines":{"18":[["gnuplot> plot                                                                   ",{}]]},"cursor":{"x":13}}],[0.257638,{"cursor":{"x":14}}],[0.305782,{"lines":{"18":[["gnuplot> plot s                                                                 ",{}]]},"cursor":{"x":15}}],[0.148558,{"lines":{"18":[["gnuplot> plot si                                                                ",{}]]},"cursor":{"x":16}}],[0.198934,{"lines":{"18":[["gnuplot> plot sin                                                               ",{}]]},"cursor":{"x":17}}],[0.573343,{"lines":{"18":[["gnuplot> plot sin(                                                              ",{}]]},"cursor":{"x":18}}],[0.123483,{"lines":{"18":[["gnuplot> plot sin(x                                                             ",{}]]},"cursor":{"x":19}}],[0.286917,{"lines":{"18":[["gnuplot> plot sin(x)                                                            ",{}]]},"cursor":{"x":20}}],[0.39285,{"lines":{"1":[["Terminal type set to 'qt'                                                       ",{}]],"2":[["gnuplot> set terminal dumb                                                      ",{}]],"3":[["Terminal type set to 'dumb'                                                     ",{}]],"4":[["Options are 'feed  size 79, 24'                                                 ",{}]],"5":[["gnuplot> # 2d plot                                                              ",{}]],"6":[["gnuplot> plot sin(x)                                                            ",{}]],"7":[["                                                                                ",{}]],"9":[["                                                                                ",{}]],"10":[["    1 ++---------------***---------------+---**-----------+--------**-----++    ",{}]],"11":[["      +                *  *              +  *  **         +  sin(x) ****** +    ",{}]],"12":[["  0.8 ++              *   *                 *    *               *    *   ++    ",{}]],"13":[["      |              *     *               *     *               *     *   |    ",{}]],"14":[["  0.6 *+             *      *              *     *               *     *  ++    ",{}]],"15":[["      |*             *      *             *       *             *       *  |    ",{}]],"16":[["  0.4 +*            *       *             *       *             *       * ++    ",{}]],"17":[["      |*            *        *            *        *           *        *  |    ",{}]],"18":[["  0.2 +*           *         *            *        *           *         *++    ",{}]],"19":[["      | *          *          *          *         *          *          * |    ",{}]],"20":[["    0 ++*          *          *         *           *         *           *+    ",{}]],"21":[[" -0.2 ++ *         *          *         *           *         *           *+    ",{}]],"22":[["      |  *        *           *        *             *        *           *|    ",{}]],"23":[[" -0                                                                             ",{}]]},"cursor":{"x":3,"y":23}}],[4.5e-05,{"lines":{"1":[["    1 ++---------------***---------------+---**-----------+--------**-----++    ",{}]],"2":[["      +                *  *              +  *  **         +  sin(x) ****** +    ",{}]],"3":[["  0.8 ++              *   *                 *    *               *    *   ++    ",{}]],"4":[["      |              *     *               *     *               *     *   |    ",{}]],"5":[["  0.6 *+             *      *              *     *               *     *  ++    ",{}]],"6":[["      |*             *      *             *       *             *       *  |    ",{}]],"7":[["  0.4 +*            *       *             *       *             *       * ++    ",{}]],"8":[["      |*            *        *            *        *           *        *  |    ",{}]],"9":[["  0.2 +*           *         *            *        *           *         *++    ",{}]],"10":[["      | *          *          *          *         *          *          * |    ",{}]],"11":[["    0 ++*          *          *         *           *         *           *+    ",{}]],"12":[[" -0.2 ++ *         *          *         *           *         *           *+    ",{}]],"13":[["      |  *        *           *        *             *        *           *|    ",{}]],"14":[[" -0.4 ++ *        *            *       *             *       *            *+    ",{}]],"15":[["      |  *       *              *      *             *      *              *    ",{}]],"16":[[" -0.6 ++  *      *              *      *             *      *             +*    ",{}]],"17":[["      |    *    *               *     *               *     *              |    ",{}]],"18":[[" -0.8 ++   *    *                *   *                 *   *              ++    ",{}]],"19":[["      +     *  *       +         **  *   +             *  *                +    ",{}]],"20":[["   -1 ++-----**--------+-----------**----+--------------***---------------++    ",{}]],"21":[["     -10              -5                 0                5                10   ",{}]],"22":[["                                                                                ",{}]],"23":[["gnuplot>                                                                        ",{}]]},"cursor":{"x":9}}],[2.01206,{"lines":{"23":[["gnuplot> #                                                                      ",{}]]},"cursor":{"x":10}}],[0.898474,{"lines":{"23":[["gnuplot> #3                                                                     ",{}]]},"cursor":{"x":11}}],[0.300142,{"lines":{"23":[["gnuplot> #3d                                                                    ",{}]]},"cursor":{"x":12}}],[0.218454,{"cursor":{"x":13}}],[0.684294,{"cursor":{"x":12}}],[0.15677,{"lines":{"23":[["gnuplot> #3                                                                     ",{}]]},"cursor":{"x":11}}],[0.139722,{"lines":{"23":[["gnuplot> #                                                                      ",{}]]},"cursor":{"x":10}}],[0.451451,{"cursor":{"x":11}}],[0.302763,{"lines":{"23":[["gnuplot> # 3                                                                    ",{}]]},"cursor":{"x":12}}],[0.465493,{"lines":{"23":[["gnuplot> # 3d                                                                   ",{}]]},"cursor":{"x":13}}],[0.131681,{"cursor":{"x":14}}],[0.246718,{"lines":{"23":[["gnuplot> # 3d p                                                                 ",{}]]},"cursor":{"x":15}}],[0.277535,{"lines":{"23":[["gnuplot> # 3d pl                                                                ",{}]]},"cursor":{"x":16}}],[0.541578,{"lines":{"23":[["gnuplot> # 3d plo                                                               ",{}]]},"cursor":{"x":17}}],[0.15669,{"lines":{"23":[["gnuplot> # 3d plot                                                              ",{}]]},"cursor":{"x":18}}],[0.375581,{"lines":{"0":[["    1 ++---------------***---------------+---**-----------+--------**-----++    ",{}]],"1":[["      +                *  *              +  *  **         +  sin(x) ****** +    ",{}]],"2":[["  0.8 ++              *   *                 *    *               *    *   ++    ",{}]],"3":[["      |              *     *               *     *               *     *   |    ",{}]],"4":[["  0.6 *+             *      *              *     *               *     *  ++    ",{}]],"5":[["      |*             *      *             *       *             *       *  |    ",{}]],"6":[["  0.4 +*            *       *             *       *             *       * ++    ",{}]],"7":[["      |*            *        *            *        *           *        *  |    ",{}]],"8":[["  0.2 +*           *         *            *        *           *         *++    ",{}]],"9":[["      | *          *          *          *         *          *          * |    ",{}]],"10":[["    0 ++*          *          *         *           *         *           *+    ",{}]],"11":[[" -0.2 ++ *         *          *         *           *         *           *+    ",{}]],"12":[["      |  *        *           *        *             *        *           *|    ",{}]],"13":[[" -0.4 ++ *        *            *       *             *       *            *+    ",{}]],"14":[["      |  *       *              *      *             *      *              *    ",{}]],"15":[[" -0.6 ++  *      *              *      *             *      *             +*    ",{}]],"16":[["      |    *    *               *     *               *     *              |    ",{}]],"17":[[" -0.8 ++   *    *                *   *                 *   *              ++    ",{}]],"18":[["      +     *  *       +         **  *   +             *  *                +    ",{}]],"19":[["   -1 ++-----**--------+-----------**----+--------------***---------------++    ",{}]],"20":[["     -10              -5                 0                5                10   ",{}]],"21":[["                                                                                ",{}]],"22":[["gnuplot> # 3d plot                                                              ",{}]],"23":[["gnuplot>                                                                        ",{}]]},"cursor":{"x":9}}],[0.412625,{"lines":{"23":[["gnuplot> s                                                                      ",{}]]},"cursor":{"x":10}}],[0.08393399999999999,{"lines":{"23":[["gnuplot> sp                                                                     ",{}]]},"cursor":{"x":11}}],[0.243637,{"lines":{"23":[["gnuplot> spl                                                                    ",{}]]},"cursor":{"x":12}}],[0.15944,{"lines":{"23":[["gnuplot> splo                                                                   ",{}]]},"cursor":{"x":13}}],[0.129789,{"lines":{"23":[["gnuplot> splot                                                                  ",{}]]},"cursor":{"x":14}}],[0.138817,{"cursor":{"x":15}}],[0.9287530000000001,{"lines":{"23":[["gnuplot> splot x                                                                ",{}]]},"cursor":{"x":16}}],[0.306001,{"lines":{"23":[["gnuplot> splot x*                                                               ",{}]]},"cursor":{"x":17}}],[0.573946,{"lines":{"23":[["gnuplot> splot x*y                                                              ",{}]]},"cursor":{"x":18}}],[0.422841,{"lines":{"0":[["      +                *  *              +  *  **         +  sin(x) ****** +    ",{}]],"1":[["  0.8 ++              *   *                 *    *               *    *   ++    ",{}]],"2":[["      |              *     *               *     *               *     *   |    ",{}]],"3":[["  0.6 *+             *      *              *     *               *     *  ++    ",{}]],"4":[["      |*             *      *             *       *             *       *  |    ",{}]],"5":[["  0.4 +*            *       *             *       *             *       * ++    ",{}]],"6":[["      |*            *        *            *        *           *        *  |    ",{}]],"7":[["  0.2 +*           *         *            *        *           *         *++    ",{}]],"8":[["      | *          *          *          *         *          *          * |    ",{}]],"9":[["    0 ++*          *          *         *           *         *           *+    ",{}]],"10":[[" -0.2 ++ *         *          *         *           *         *           *+    ",{}]],"11":[["      |  *        *           *        *             *        *           *|    ",{}]],"12":[[" -0.4 ++ *        *            *       *             *       *            *+    ",{}]],"13":[["      |  *       *              *      *             *      *              *    ",{}]],"14":[[" -0.6 ++  *      *              *      *             *      *             +*    ",{}]],"15":[["      |    *    *               *     *               *     *              |    ",{}]],"16":[[" -0.8 ++   *    *                *   *                 *   *              ++    ",{}]],"17":[["      +     *  *       +         **  *   +             *  *                +    ",{}]],"18":[["   -1 ++-----**--------+-----------**----+--------------***---------------++    ",{}]],"19":[["     -10              -5                 0                5                10   ",{}]],"20":[["                                                                                ",{}]],"21":[["gnuplot> # 3d plot                                                              ",{}]],"22":[["gnuplot> splot x*y                                                              ",{}]],"23":[["                                                                                ",{}]]},"cursor":{"x":0}}],[0.006178000000000006,{"lines":{"0":[["                                                                                ",{}]],"1":[["                                                                                ",{}]],"2":[["                                                                                ",{}]],"3":[["                                                         x*y ******             ",{}]],"4":[["                                                                                ",{}]],"5":[["                                                                ****            ",{}]],"6":[["                                                     **************|            ",{}]],"7":[["      100  *******                        ***********************  |            ",{}]],"8":[["           | **************************************************    |            ",{}]],"9":[["       50  |+     *******************************************      |            ",{}]],"10":[["      -50  |+         *************************************        |            ",{}]],"11":[["           |              ----+**** ****-**************            |            ",{}]],"12":[["     -100  |+         ----  +      ******************---------     |            ",{}]],"13":[["           |      ----++               ************     +   ------ 10           ",{}]],"14":[["           | -----                        *******     ------  5                 ",{}]],"15":[["      -10  +--------+-+---------------        |  ----- + 0                      ",{}]],"16":[["                -5        0  +-+      -+------|-- +-5                           ",{}]],"17":[["                                   5  +      +-10                               ",{}]],"18":[["                                          10                                    ",{}]],"19":[["                                                                                ",{}]],"21":[["                                                                                ",{}]],"22":[["                                                                                ",{}]],"23":[["gnuplot>                                                                        ",{}]]},"cursor":{"x":9}}],[2.281793,{"lines":{"2":[["                                                         x*y ******             ",{}]],"3":[["                                                                                ",{}]],"4":[["                                                                ****            ",{}]],"5":[["                                                     **************|            ",{}]],"6":[["      100  *******                        ***********************  |            ",{}]],"7":[["           | **************************************************    |            ",{}]],"8":[["       50  |+     *******************************************      |            ",{}]],"9":[["      -50  |+         *************************************        |            ",{}]],"10":[["           |              ----+**** ****-**************            |            ",{}]],"11":[["     -100  |+         ----  +      ******************---------     |            ",{}]],"12":[["           |      ----++               ************     +   ------ 10           ",{}]],"13":[["           | -----                        *******     ------  5                 ",{}]],"14":[["      -10  +--------+-+---------------        |  ----- + 0                      ",{}]],"15":[["                -5        0  +-+      -+------|-- +-5                           ",{}]],"16":[["                                   5  +      +-10                               ",{}]],"17":[["                                          10                                    ",{}]],"18":[["                                                                                ",{}]],"22":[["gnuplot>                                                                        ",{}]],"23":[["                                                                                ",{}]]},"cursor":{"x":0}}]]